gnote/__init__.py
gnote/cli.py
gnote-0.3.2.dist-info/entry_points.txt
gnote-0.3.2.dist-info/WHEEL
gnote-0.3.2.dist-info/METADATA
gnote-0.3.2.dist-info/RECORD
